geflex_db/__init__.py
geflex_db/_new_ast.py
geflex_db/acnt.py
geflex_db/file_tables.py
geflex_db/ftables.py
geflex_db/mini_storage.py
geflex_db/path.py
geflex_db/saveable_tables.py
geflex_db/tables.py
geflex_db/utils.py
geflex_db-0.16.1.dist-info/METADATA
geflex_db-0.16.1.dist-info/RECORD
geflex_db-0.16.1.dist-info/WHEEL
geflex_db-0.16.1.dist-info/top_level.txt
