Metadata-Version: 2.1
Name: geflex-db
Version: 0.16.1
Summary: Simple tables and file objects for data storage and processing.
Home-page: https://github.com/geflex/geflex_db
Author: geflex
Author-email: geflikh.d.s@gmail.com
License: Apache 2.0, see LICENSE file
Platform: UNKNOWN
